myfitnesspal_to_sqlite/__init__.py
myfitnesspal_to_sqlite/cli.py
myfitnesspal_to_sqlite/utils.py
myfitnesspal_to_sqlite-0.2.2.dist-info/LICENSE
myfitnesspal_to_sqlite-0.2.2.dist-info/METADATA
myfitnesspal_to_sqlite-0.2.2.dist-info/WHEEL
myfitnesspal_to_sqlite-0.2.2.dist-info/entry_points.txt
myfitnesspal_to_sqlite-0.2.2.dist-info/top_level.txt
myfitnesspal_to_sqlite-0.2.2.dist-info/RECORD
