Metadata-Version: 2.1
Name: myfitnesspal-to-sqlite
Version: 0.2.2
Summary: Save data from MyFitnessPal to a SQLite database
Home-page: https://github.com/seem/myfitnesspal-to-sqlite
Author: Wasim Lorgat
License: Apache License, Version 2.0
Project-URL: Issues, https://github.com/seem/myfitnesspal-to-sqlite/issues
Project-URL: CI, https://github.com/seem/myfitnesspal-to-sqlite/actions
Project-URL: Changelog, https://github.com/seem/myfitnesspal-to-sqlite/releases
Platform: UNKNOWN
Requires-Dist: click
Requires-Dist: sqlite-utils (>=3.0)
Requires-Dist: myfitnesspal
Provides-Extra: test
Requires-Dist: pytest ; extra == 'test'
